MANIFEST.in
README.rst
setup.py
docs/HISTORY.txt
docs/INSTALL.txt
docs/LICENSE.GPL
docs/LICENSE.txt
redturtle/__init__.py
redturtle.sendto_extension.egg-info/PKG-INFO
redturtle.sendto_extension.egg-info/SOURCES.txt
redturtle.sendto_extension.egg-info/dependency_links.txt
redturtle.sendto_extension.egg-info/entry_points.txt
redturtle.sendto_extension.egg-info/namespace_packages.txt
redturtle.sendto_extension.egg-info/not-zip-safe
redturtle.sendto_extension.egg-info/requires.txt
redturtle.sendto_extension.egg-info/top_level.txt
redturtle/sendto_extension/__init__.py
redturtle/sendto_extension/configure.zcml
redturtle/sendto_extension/interfaces.py
redturtle/sendto_extension/permissions.zcml
redturtle/sendto_extension/testing.py
redturtle/sendto_extension/vocabularies.py
redturtle/sendto_extension/browser/__init__.py
redturtle/sendto_extension/browser/configure.zcml
redturtle/sendto_extension/browser/controlpanel.py
redturtle/sendto_extension/browser/query.py
redturtle/sendto_extension/browser/sendto.pt
redturtle/sendto_extension/browser/sendto.py
redturtle/sendto_extension/browser/resources/group.png
redturtle/sendto_extension/browser/resources/mail_icon.png
redturtle/sendto_extension/browser/resources/sendto.css
redturtle/sendto_extension/browser/resources/user.png
redturtle/sendto_extension/locales/rebuildPo.sh
redturtle/sendto_extension/locales/redturtle.sendto_extension-manual.pot
redturtle/sendto_extension/locales/redturtle.sendto_extension.pot
redturtle/sendto_extension/locales/it/LC_MESSAGES/redturtle.sendto_extension.mo
redturtle/sendto_extension/locales/it/LC_MESSAGES/redturtle.sendto_extension.po
redturtle/sendto_extension/profiles/default/actions.xml
redturtle/sendto_extension/profiles/default/browserlayer.xml
redturtle/sendto_extension/profiles/default/controlpanel.xml
redturtle/sendto_extension/profiles/default/cssregistry.xml
redturtle/sendto_extension/profiles/default/metadata.xml
redturtle/sendto_extension/profiles/default/registry.xml
redturtle/sendto_extension/profiles/default/rolemap.xml
redturtle/sendto_extension/profiles/default/skins.xml
redturtle/sendto_extension/skins/redturtle_sendto_extension/sendto.py
redturtle/sendto_extension/skins/redturtle_sendto_extension/sendto_form.py
redturtle/sendto_extension/tests/__init__.py
redturtle/sendto_extension/tests/base.py
redturtle/sendto_extension/tests/test_anonymous.py