Metadata-Version: 1.1
Name: redturtle.sendto-extension
Version: 2.0.0b2
Summary: An extension for the "Send this" Plone document action
Home-page: http://plone.org/products/redturtle.sendto_extension
Author: Redturtle Technology
Author-email: sviluppoplone@redturtle.it
License: GPL
Keywords: plone plonegov sendto mail users groups
Platform: UNKNOWN
Classifier: Development Status :: 4 - Beta
Classifier: Framework :: Plone
Classifier: Framework :: Plone :: 4.3
Classifier: Programming Language :: Python
Classifier: Topic :: Software Development :: Libraries :: Python Modules
